DSToolbox/__init__.py
DSToolbox/df_utils.py
DataScience_ToolBox-0.1.2.dist-info/LICENSE
DataScience_ToolBox-0.1.2.dist-info/METADATA
DataScience_ToolBox-0.1.2.dist-info/WHEEL
DataScience_ToolBox-0.1.2.dist-info/top_level.txt
DataScience_ToolBox-0.1.2.dist-info/RECORD
