Metadata-Version: 2.1
Name: DataScience-ToolBox
Version: 0.1.2
Summary: A set of python modules for machine learning and data mining
Home-page: https://github.com/DataLovecraft/DataScience-Tools
Author: Johann Augustine
License: UNKNOWN
Platform: UNKNOWN
Classifier: Programming Language :: Python :: 3
Classifier: License :: OSI Approved :: MIT License
Classifier: Operating System :: OS Independent
Requires-Python: >=3.6
Requires-Dist: numpy
Requires-Dist: pandas
Requires-Dist: spacy
